tokenator/__init__.py
tokenator/anthropic/client_anthropic.py
tokenator/anthropic/stream_interceptors.py
tokenator/base_wrapper.py
tokenator/create_migrations.py
tokenator/gemini/__init__.py
tokenator/gemini/client_gemini.py
tokenator/gemini/stream_interceptors.py
tokenator/migrations/env.py
tokenator/migrations/script.py.mako
tokenator/migrations/versions/f028b8155fed_adding_detailed_input_and_output_token_.py
tokenator/migrations/versions/f6f1f2437513_initial_migration.py
tokenator/migrations.py
tokenator/models.py
tokenator/openai/client_openai.py
tokenator/openai/stream_interceptors.py
tokenator/schemas.py
tokenator/state.py
tokenator/usage.py
tokenator/utils.py
tokenator-0.2.1.dist-info/LICENSE
tokenator-0.2.1.dist-info/METADATA
tokenator-0.2.1.dist-info/WHEEL
tokenator-0.2.1.dist-info/RECORD
