Metadata-Version: 2.3
Name: tokenator
Version: 0.2.1
Summary: Token usage and cost tracking for LLMs
License: MIT
Author: Ujjwal Maheshwari
Author-email: ujjwalm29@gmail.com
Requires-Python: >=3.9,<4.0
Classifier: License :: OSI Approved :: MIT License
Classifier: Programming Language :: Python :: 3
Classifier: Programming Language :: Python :: 3.9
Classifier: Programming Language :: Python :: 3.10
Classifier: Programming Language :: Python :: 3.11
Classifier: Programming Language :: Python :: 3.12
Classifier: Programming Language :: Python :: 3.13
Requires-Dist: alembic (>=1.13.0,<2.0.0)
Requires-Dist: anthropic (>=0.43.0,<0.44.0)
Requires-Dist: google-genai (>=1.3.0,<2.0.0)
Requires-Dist: ipython
Requires-Dist: openai (>=1.59.0,<2.0.0)
Requires-Dist: requests (>=2.32.3,<3.0.0)
Requires-Dist: sqlalchemy (>=2.0.0,<3.0.0)
